{
	"description": "项目配置文件",
	"packOptions": {
		"ignore": []
	},
	"setting": {
		"urlCheck": true,
		"es6": true,
		"postcss": true,
		"minified": true,
		"newFeature": true,
		"autoAudits": false
	},
	"compileType": "miniprogram",
	"libVersion": "2.6.5",
	"appid": "wxbd01dc5b31432f51",
	"projectname": "%E7%89%A9%E6%B5%81",
	"debugOptions": {
		"hidedInDevtools": []
	},
	"isGameTourist": false,
	"simulatorType": "wechat",
	"simulatorPluginLibVersion": {},
	"condition": {
		"search": {
			"current": -1,
			"list": []
		},
		"conversation": {
			"current": -1,
			"list": []
		},
		"plugin": {
			"current": -1,
			"list": []
		},
		"game": {
			"currentL": -1,
			"list": []
		},
		"gamePlugin": {
			"current": -1,
			"list": []
		},
		"miniprogram": {
			"current": -1,
			"list": [
				{
					"id": -1,
					"name": "pages/mine/mine",
					"pathName": "pages/mine/mine",
					"query": "",
					"scene": null
				},
				{
					"id": -1,
					"name": "pages/details/details",
					"pathName": "pages/details/details",
					"query": "",
					"scene": null
				},
				{
					"id": 2,
					"name": "pages/goods/goods",
					"pathName": "pages/goods/goods",
					"query": "",
					"scene": null
				},
				{
					"id": -1,
					"name": "pages/map/map",
					"pathName": "pages/map/map",
					"query": "",
					"scene": null
				},
				{
					"id": -1,
					"name": "pages/index/index",
					"pathName": "pages/index/index",
					"scene": null
				}
			]
		}
	}
}